ampworks/__init__.py
ampworks/cli.py
ampworks/math.py
ampworks/dqdv/__init__.py
ampworks/dqdv/gui_files/__init__.py
ampworks/dqdv/gui_files/_gui.py
ampworks/dqdv/gui_files/assets/styles.css
ampworks/dqdv/gui_files/layout/__init__.py
ampworks/dqdv/gui_files/layout/navbar.py
ampworks/dqdv/gui_files/layout/sidebar.py
ampworks/dqdv/gui_files/pages/__init__.py
ampworks/dqdv/gui_files/pages/components.py
ampworks/dqdv/gui_files/pages/dqv_analysis.py
ampworks/dqdv/gui_files/pages/figures.py
ampworks/dqdv/gui_files/pages/user_guide.py
ampworks/gitt/__init__.py
ampworks/gitt/_dataclasses.py
ampworks/gitt/_extract_params.py
ampworks/plotutils/__init__.py
ampworks/utils/__init__.py
ampworks-0.0.1.dist-info/LICENSE
ampworks-0.0.1.dist-info/METADATA
ampworks-0.0.1.dist-info/WHEEL
ampworks-0.0.1.dist-info/entry_points.txt
ampworks-0.0.1.dist-info/top_level.txt
ampworks-0.0.1.dist-info/RECORD
