Metadata-Version: 2.2
Name: ampworks
Version: 0.0.1
Summary: Processing and visualization tools for battery experiments.
Author: Corey R. Randall
Author-email: corey.randall@nrel.gov
Maintainer: Corey R. Randall
Maintainer-email: corey.randall@nrel.gov
License: BSD 3-Clause License
Project-URL: Homepage, https://github.com/NREL/ampworks
Project-URL: Documentation, https://github.com/NREL/ampworks
Project-URL: Repository, https://github.com/NREL/ampworks
Project-URL: Issues, https://github.com/NREL/ampworks/issues
Keywords: battery,analysis,data,ICA,dQdV,GITT
Classifier: Development Status :: 3 - Alpha
Classifier: Intended Audience :: Science/Research
Classifier: License :: OSI Approved :: BSD License
Classifier: Programming Language :: Python :: 3
Classifier: Programming Language :: Python :: 3.9
Classifier: Programming Language :: Python :: 3.10
Classifier: Programming Language :: Python :: 3.11
Classifier: Programming Language :: Python :: 3.12
Classifier: Programming Language :: Python :: 3.13
Requires-Python: <3.14,>=3.9
License-File: LICENSE
Requires-Dist: numpy
Requires-Dist: scipy>=1.13
Requires-Dist: pandas
Requires-Dist: openpyxl
Requires-Dist: matplotlib
Provides-Extra: gui
Requires-Dist: dash; extra == "gui"
Requires-Dist: dash-ag-grid; extra == "gui"
Requires-Dist: dash-extensions; extra == "gui"
Requires-Dist: dash-breakpoints; extra == "gui"
Requires-Dist: dash-bootstrap-templates; extra == "gui"
Requires-Dist: dash-bootstrap-components; extra == "gui"
Provides-Extra: docs
Requires-Dist: sphinx; extra == "docs"
Requires-Dist: myst-nb; extra == "docs"
Requires-Dist: numpydoc; extra == "docs"
Requires-Dist: sphinx-design; extra == "docs"
Requires-Dist: sphinx-autoapi; extra == "docs"
Requires-Dist: sphinx-copybutton; extra == "docs"
Requires-Dist: pydata-sphinx-theme; extra == "docs"
Provides-Extra: tests
Requires-Dist: pytest; extra == "tests"
Requires-Dist: pytest-cov; extra == "tests"
Requires-Dist: pytest-xdist; extra == "tests"
Provides-Extra: dev
Requires-Dist: nox; extra == "dev"
Requires-Dist: flake8; extra == "dev"
Requires-Dist: autopep8; extra == "dev"
Requires-Dist: codespell; extra == "dev"
Requires-Dist: genbadge[all]; extra == "dev"
Requires-Dist: ampworks[docs,gui,tests]; extra == "dev"
